Metadata-Version: 1.1
Name: adhoctx
Version: 0.0.1
Summary: An adhoc context object
Home-page: https://github.com/bailaohe/adhoctx
Author: He Bai
Author-email: bailaohe@gmail.com
License: UNKNOWN
Keywords: context,dict
Platform: any
Classifier: Development Status :: 4 - Beta
Classifier: Intended Audience :: Developers
Classifier: License :: OSI Approved :: Apache Software License
Classifier: Programming Language :: Python :: 3
Classifier: Topic :: Software Development :: Libraries :: Python Modules
Classifier: Operating System :: Unix
Classifier: Operating System :: MacOS :: MacOS X
Classifier: Operating System :: Microsoft :: Windows
Classifier: Operating System :: POSIX
